{
	"configurations" : 
	[
		{
			"directories" : 
			[
				{
					"build" : ".",
					"childIndexes" : 
					[
						1
					],
					"jsonFile" : "directory-.-f5ebdc15457944623624.json",
					"minimumCMakeVersion" : 
					{
						"string" : "3.14"
					},
					"projectIndex" : 0,
					"source" : "."
				},
				{
					"build" : "tests",
					"childIndexes" : 
					[
						2
					],
					"jsonFile" : "directory-tests-b01f6abb0ab61427ef3b.json",
					"minimumCMakeVersion" : 
					{
						"string" : "3.14"
					},
					"parentIndex" : 0,
					"projectIndex" : 1,
					"source" : "tests",
					"targetIndexes" : 
					[
						2,
						3,
						4,
						5,
						6,
						7,
						8,
						9,
						10,
						11,
						12,
						13,
						14,
						15,
						16,
						17,
						18,
						19,
						20,
						21,
						22,
						23,
						24,
						25,
						26,
						27,
						28,
						29,
						30,
						31,
						32,
						33
					]
				},
				{
					"build" : "_deps/catch2-build",
					"childIndexes" : 
					[
						3
					],
					"jsonFile" : "directory-_deps.catch2-build-b1208c190cea666efc56.json",
					"minimumCMakeVersion" : 
					{
						"string" : "3.5"
					},
					"parentIndex" : 1,
					"projectIndex" : 2,
					"source" : "build/_deps/catch2-src"
				},
				{
					"build" : "_deps/catch2-build/src",
					"jsonFile" : "directory-_deps.catch2-build.src-cd0b0c6cd8598cf9777c.json",
					"minimumCMakeVersion" : 
					{
						"string" : "3.5"
					},
					"parentIndex" : 2,
					"projectIndex" : 2,
					"source" : "build/_deps/catch2-src/src",
					"targetIndexes" : 
					[
						0,
						1
					]
				}
			],
			"name" : "",
			"projects" : 
			[
				{
					"childIndexes" : 
					[
						1
					],
					"directoryIndexes" : 
					[
						0
					],
					"name" : "os-hw3"
				},
				{
					"childIndexes" : 
					[
						2
					],
					"directoryIndexes" : 
					[
						1
					],
					"name" : "os-hw3-tests",
					"parentIndex" : 0,
					"targetIndexes" : 
					[
						2,
						3,
						4,
						5,
						6,
						7,
						8,
						9,
						10,
						11,
						12,
						13,
						14,
						15,
						16,
						17,
						18,
						19,
						20,
						21,
						22,
						23,
						24,
						25,
						26,
						27,
						28,
						29,
						30,
						31,
						32,
						33
					]
				},
				{
					"directoryIndexes" : 
					[
						2,
						3
					],
					"name" : "Catch2",
					"parentIndex" : 1,
					"targetIndexes" : 
					[
						0,
						1
					]
				}
			],
			"targets" : 
			[
				{
					"directoryIndex" : 3,
					"id" : "Catch2::@fa92aa50e9bf5e1a7206",
					"jsonFile" : "target-Catch2-07e0309326e8b0057476.json",
					"name" : "Catch2",
					"projectIndex" : 2
				},
				{
					"directoryIndex" : 3,
					"id" : "Catch2WithMain::@fa92aa50e9bf5e1a7206",
					"jsonFile" : "target-Catch2WithMain-d5363310ec82617fa99f.json",
					"name" : "Catch2WithMain",
					"projectIndex" : 2
				},
				{
					"directoryIndex" : 1,
					"id" : "Continuous::@a44f0ac069e85531cdee",
					"jsonFile" : "target-Continuous-97b0e641196e569e2391.json",
					"name" : "Continuous",
					"projectIndex" : 1
				},
				{
					"directoryIndex" : 1,
					"id" : "ContinuousBuild::@a44f0ac069e85531cdee",
					"jsonFile" : "target-ContinuousBuild-95a0de8e716b3723d146.json",
					"name" : "ContinuousBuild",
					"projectIndex" : 1
				},
				{
					"directoryIndex" : 1,
					"id" : "ContinuousConfigure::@a44f0ac069e85531cdee",
					"jsonFile" : "target-ContinuousConfigure-fbc0af5ee5b7968575b9.json",
					"name" : "ContinuousConfigure",
					"projectIndex" : 1
				},
				{
					"directoryIndex" : 1,
					"id" : "ContinuousCoverage::@a44f0ac069e85531cdee",
					"jsonFile" : "target-ContinuousCoverage-22ac4a525a4159fea4da.json",
					"name" : "ContinuousCoverage",
					"projectIndex" : 1
				},
				{
					"directoryIndex" : 1,
					"id" : "ContinuousMemCheck::@a44f0ac069e85531cdee",
					"jsonFile" : "target-ContinuousMemCheck-a5fbf73bb385963e61e6.json",
					"name" : "ContinuousMemCheck",
					"projectIndex" : 1
				},
				{
					"directoryIndex" : 1,
					"id" : "ContinuousStart::@a44f0ac069e85531cdee",
					"jsonFile" : "target-ContinuousStart-4a0835c9e9532d5878b5.json",
					"name" : "ContinuousStart",
					"projectIndex" : 1
				},
				{
					"directoryIndex" : 1,
					"id" : "ContinuousSubmit::@a44f0ac069e85531cdee",
					"jsonFile" : "target-ContinuousSubmit-83c5e1fc4c4172f60dd5.json",
					"name" : "ContinuousSubmit",
					"projectIndex" : 1
				},
				{
					"directoryIndex" : 1,
					"id" : "ContinuousTest::@a44f0ac069e85531cdee",
					"jsonFile" : "target-ContinuousTest-bf7e94c01a922b557bd0.json",
					"name" : "ContinuousTest",
					"projectIndex" : 1
				},
				{
					"directoryIndex" : 1,
					"id" : "ContinuousUpdate::@a44f0ac069e85531cdee",
					"jsonFile" : "target-ContinuousUpdate-a8b34563c42da29d47c0.json",
					"name" : "ContinuousUpdate",
					"projectIndex" : 1
				},
				{
					"directoryIndex" : 1,
					"id" : "Experimental::@a44f0ac069e85531cdee",
					"jsonFile" : "target-Experimental-cafe53d83073479c9fd9.json",
					"name" : "Experimental",
					"projectIndex" : 1
				},
				{
					"directoryIndex" : 1,
					"id" : "ExperimentalBuild::@a44f0ac069e85531cdee",
					"jsonFile" : "target-ExperimentalBuild-e33d04a1775140094eec.json",
					"name" : "ExperimentalBuild",
					"projectIndex" : 1
				},
				{
					"directoryIndex" : 1,
					"id" : "ExperimentalConfigure::@a44f0ac069e85531cdee",
					"jsonFile" : "target-ExperimentalConfigure-bf75e94ebed31f37fd67.json",
					"name" : "ExperimentalConfigure",
					"projectIndex" : 1
				},
				{
					"directoryIndex" : 1,
					"id" : "ExperimentalCoverage::@a44f0ac069e85531cdee",
					"jsonFile" : "target-ExperimentalCoverage-d55ab07330a8fa712c03.json",
					"name" : "ExperimentalCoverage",
					"projectIndex" : 1
				},
				{
					"directoryIndex" : 1,
					"id" : "ExperimentalMemCheck::@a44f0ac069e85531cdee",
					"jsonFile" : "target-ExperimentalMemCheck-182ce4eb3c1bc2ff0724.json",
					"name" : "ExperimentalMemCheck",
					"projectIndex" : 1
				},
				{
					"directoryIndex" : 1,
					"id" : "ExperimentalStart::@a44f0ac069e85531cdee",
					"jsonFile" : "target-ExperimentalStart-af344692b464700f0f03.json",
					"name" : "ExperimentalStart",
					"projectIndex" : 1
				},
				{
					"directoryIndex" : 1,
					"id" : "ExperimentalSubmit::@a44f0ac069e85531cdee",
					"jsonFile" : "target-ExperimentalSubmit-1305449e41e43ed1f6b4.json",
					"name" : "ExperimentalSubmit",
					"projectIndex" : 1
				},
				{
					"directoryIndex" : 1,
					"id" : "ExperimentalTest::@a44f0ac069e85531cdee",
					"jsonFile" : "target-ExperimentalTest-47a024b4fd527628028a.json",
					"name" : "ExperimentalTest",
					"projectIndex" : 1
				},
				{
					"directoryIndex" : 1,
					"id" : "ExperimentalUpdate::@a44f0ac069e85531cdee",
					"jsonFile" : "target-ExperimentalUpdate-4d20c77d3ab2872941f6.json",
					"name" : "ExperimentalUpdate",
					"projectIndex" : 1
				},
				{
					"directoryIndex" : 1,
					"id" : "Nightly::@a44f0ac069e85531cdee",
					"jsonFile" : "target-Nightly-85d4f1b574dcf5e9c98a.json",
					"name" : "Nightly",
					"projectIndex" : 1
				},
				{
					"directoryIndex" : 1,
					"id" : "NightlyBuild::@a44f0ac069e85531cdee",
					"jsonFile" : "target-NightlyBuild-b2f348231a3c8317d334.json",
					"name" : "NightlyBuild",
					"projectIndex" : 1
				},
				{
					"directoryIndex" : 1,
					"id" : "NightlyConfigure::@a44f0ac069e85531cdee",
					"jsonFile" : "target-NightlyConfigure-9506697b114d9dcfb3f0.json",
					"name" : "NightlyConfigure",
					"projectIndex" : 1
				},
				{
					"directoryIndex" : 1,
					"id" : "NightlyCoverage::@a44f0ac069e85531cdee",
					"jsonFile" : "target-NightlyCoverage-9a64920b909ad1b8ea6f.json",
					"name" : "NightlyCoverage",
					"projectIndex" : 1
				},
				{
					"directoryIndex" : 1,
					"id" : "NightlyMemCheck::@a44f0ac069e85531cdee",
					"jsonFile" : "target-NightlyMemCheck-d95459b9c3f0a72bed54.json",
					"name" : "NightlyMemCheck",
					"projectIndex" : 1
				},
				{
					"directoryIndex" : 1,
					"id" : "NightlyMemoryCheck::@a44f0ac069e85531cdee",
					"jsonFile" : "target-NightlyMemoryCheck-26cde6acad4455c06144.json",
					"name" : "NightlyMemoryCheck",
					"projectIndex" : 1
				},
				{
					"directoryIndex" : 1,
					"id" : "NightlyStart::@a44f0ac069e85531cdee",
					"jsonFile" : "target-NightlyStart-893342260a95e14aed32.json",
					"name" : "NightlyStart",
					"projectIndex" : 1
				},
				{
					"directoryIndex" : 1,
					"id" : "NightlySubmit::@a44f0ac069e85531cdee",
					"jsonFile" : "target-NightlySubmit-a3e29017072cc889a236.json",
					"name" : "NightlySubmit",
					"projectIndex" : 1
				},
				{
					"directoryIndex" : 1,
					"id" : "NightlyTest::@a44f0ac069e85531cdee",
					"jsonFile" : "target-NightlyTest-95e2cd6d360735ecded4.json",
					"name" : "NightlyTest",
					"projectIndex" : 1
				},
				{
					"directoryIndex" : 1,
					"id" : "NightlyUpdate::@a44f0ac069e85531cdee",
					"jsonFile" : "target-NightlyUpdate-c4d9ef13603c26c9bcfc.json",
					"name" : "NightlyUpdate",
					"projectIndex" : 1
				},
				{
					"directoryIndex" : 1,
					"id" : "malloc_1_test::@a44f0ac069e85531cdee",
					"jsonFile" : "target-malloc_1_test-73061a9f9bd01c078d48.json",
					"name" : "malloc_1_test",
					"projectIndex" : 1
				},
				{
					"directoryIndex" : 1,
					"id" : "malloc_2_test::@a44f0ac069e85531cdee",
					"jsonFile" : "target-malloc_2_test-c23176c9520dff3ec4a3.json",
					"name" : "malloc_2_test",
					"projectIndex" : 1
				},
				{
					"directoryIndex" : 1,
					"id" : "malloc_3_test::@a44f0ac069e85531cdee",
					"jsonFile" : "target-malloc_3_test-c553cfa8d7afd446a037.json",
					"name" : "malloc_3_test",
					"projectIndex" : 1
				},
				{
					"directoryIndex" : 1,
					"id" : "malloc_4_test::@a44f0ac069e85531cdee",
					"jsonFile" : "target-malloc_4_test-66b45993f8776213c442.json",
					"name" : "malloc_4_test",
					"projectIndex" : 1
				}
			]
		}
	],
	"kind" : "codemodel",
	"paths" : 
	{
		"build" : "/home/giladeldor/Hafaala4/build",
		"source" : "/home/giladeldor/Hafaala4"
	},
	"version" : 
	{
		"major" : 2,
		"minor" : 4
	}
}
